{
  "metadata": {
    "case_name": "Nanavati v. State",
    "case_year": 1961,
    "court": "Supreme Court of India",
    "judges": [
      "SUBBA RAO, J."
    ],
    "case_number": "Criminal Appeal No. 195 of 1960",
    "date_of_judgment": "1961-11-24"
  },
  "facts": [
    {
      "id": "f1",
      "text": "Appellant Nanavati was second in command of Indian Naval Ship Mysore. Married Sylvia in 1949 in England. Three children: boy aged 9 1/2, girl 5 1/2, boy 3 years.",
      "type": "background",
      "date": null,
      "source": "court"
    },
    {
      "id": "f2",
      "text": "Couple lived in different places due to service exigencies, finally shifted to Bombay. Deceased Ahuja, 34, unmarried businessman in automobiles, resided in Shreyas till 1957, then Jivan Jyot.",
      "type": "background",
      "date": null,
      "source": "prosecution"
    },
    {
      "id": "f3",
      "text": "In 1956, common friends Agniks introduced Ahuja and sister to Nanavatis. Friendship developed between Ahuja and Sylvia, culminating in illicit intimacy.",
      "type": "material",
      "date": null,
      "source": "prosecution"
    },
    {
      "id": "f4",
      "text": "On April 27, 1959, Sylvia confessed illicit intimacy with Ahuja to Nanavati.",
      "type": "material",
      "date": "1959-04-27",
      "source": "prosecution"
    },
    {
      "id": "f5",
      "text": "Enraged, Nanavati went to ship, took semi-automatic revolver and six cartridges on false pretext, loaded it, went to Ahuja's flat, entered bedroom, shot him dead. Surrendered to police.",
      "type": "material",
      "date": "1959-04-27",
      "source": "prosecution"
    },
    {
      "id": "f6",
      "text": "Accused away with ship April 6-18, 1959. Returned, went to Ahmednagar with wife, brother. Noticed wife strange, unresponsive. On April 27, after lunch, questioned fidelity, she indicated unfaithful, guessed Ahuja.",
      "type": "background",
      "date": "1959-04-27",
      "source": "petitioner"
    },
    {
      "id": "f7",
      "text": "Decided to settle with Ahuja. Dropped wife and children at cinema. Went to ship for dog medicine, got revolver pretending drive to Ahmednagar alone at night. Put in envelope.",
      "type": "procedural",
      "date": "1959-04-27",
      "source": "petitioner"
    },
    {
      "id": "f8",
      "text": "Went to Ahuja's office, not there, then flat. Servant opened, went to bedroom, shut door. Asked if marry Sylvia and care for children. Ahuja retorted 'Am I to marry every woman I sleep with?'. Enraged, threatened to thrash. Ahuja moved for envelope, struggle, two shots accidental.",
      "type": "disputed",
      "date": "1959-04-27",
      "source": "petitioner"
    },
    {
      "id": "f9",
      "text": "Accused charged under s.302 and s.304 Part I IPC, tried by Sessions Judge Greater Bombay with special jury.",
      "type": "procedural",
      "date": null,
      "source": "court"
    },
    {
      "id": "f10",
      "text": "Jury verdict not guilty by 8:1 under both sections.",
      "type": "procedural",
      "date": null,
      "source": "court"
    },
    {
      "id": "f11",
      "text": "Sessions Judge disagreed, as majority verdict such that no reasonable body could bring it on evidence. Submitted under s.307 CrPC to Bombay High Court.",
      "type": "procedural",
      "date": null,
      "source": "lower_court"
    },
    {
      "id": "f12",
      "text": "Bombay HC division bench (Shelat and Naik JJ) held guilty under s.302 IPC, sentenced to rigorous life imprisonment. Shelat J found misdirections, reviewed evidence. Naik J found verdict unreasonable.",
      "type": "procedural",
      "date": "1960-03-11",
      "source": "lower_court"
    },
    {
      "id": "f13",
      "text": "Both HC judges agreed no case to reduce to culpable homicide not amounting to murder.",
      "type": "procedural",
      "date": "1960-03-11",
      "source": "lower_court"
    },
    {
      "id": "f14",
      "text": "Appeal by special leave to Supreme Court.",
      "type": "procedural",
      "date": null,
      "source": "court"
    }
  ],
  "legal_issues": [
    {
      "id": "i1",
      "text": "Whether reference under s.307 CrPC by Sessions Judge competent only on perusal of order, without considering evidence.",
      "framed_by": "petitioner"
    },
    {
      "id": "i2",
      "text": "Whether High Court under s.307 CrPC has power to set aside jury verdict on ground of misdirections in charge.",
      "framed_by": "petitioner"
    },
    {
      "id": "i3",
      "text": "Whether there were misdirections in Sessions Judge's charge to jury.",
      "framed_by": "petitioner"
    },
    {
      "id": "i4",
      "text": "Whether jury verdict perverse, such that no reasonable body could arrive at it.",
      "framed_by": "petitioner"
    },
    {
      "id": "i5",
      "text": "Whether accused acted under grave and sudden provocation, reducing offence to culpable homicide not amounting to murder.",
      "framed_by": "petitioner"
    }
  ],
  "petitioner_arguments": [
    {
      "id": "pa1",
      "text": "Under s.307 CrPC, HC decides competency of reference only on perusal of referring order, no jurisdiction to consider evidence.",
      "supporting_facts": [
        "f11"
      ],
      "legal_basis": "s.307 CrPC; Ramanugrah Singh v. King Emperor"
    },
    {
      "id": "pa2",
      "text": "HC under s.307 has no power to set aside jury verdict on misdirections.",
      "supporting_facts": [],
      "legal_basis": "s.307 CrPC; s.418, 423 CrPC"
    },
    {
      "id": "pa3",
      "text": "No misdirections in charge; charge fair to both sides.",
      "supporting_facts": [],
      "legal_basis": null
    },
    {
      "id": "pa4",
      "text": "Jury verdict not perverse; reasonable body could arrive at it. Alternatively, grave and sudden provocation.",
      "supporting_facts": [
        "f4",
        "f8"
      ],
      "legal_basis": "Exception 1 s.300 IPC"
    }
  ],
  "respondent_arguments": [
    {
      "id": "ra1",
      "text": "HC can consider entire evidence under s.307(3) CrPC after finding reference competent.",
      "supporting_facts": [
        "f11",
        "f12"
      ],
      "legal_basis": "s.307 CrPC"
    },
    {
      "id": "ra2",
      "text": "Misdirections vitiated verdict; no grave sudden provocation.",
      "supporting_facts": [],
      "legal_basis": null
    }
  ],
  "court_reasoning": [
    {
      "id": "cr1",
      "text": "Reference competent if Sessions Judge disagrees with jury and clearly opines no reasonable body could reach verdict, recording grounds. HC then considers entire evidence.",
      "addresses_issue": "i1",
      "key_observation": "Two conditions for reference satisfied ex facie."
    },
    {
      "id": "cr2",
      "text": "Under s.307(3) CrPC, HC exercises appellate-like powers, considers entire evidence, gives due weight to Judge and jury opinions. Can interfere if misdirections or verdict unreasonable/perverse.",
      "addresses_issue": "i2",
      "key_observation": "Wider jurisdiction than appeal under s.418 CrPC."
    },
    {
      "id": "cr3",
      "text": "Grave misdirections/omissions: No reference to s.105 Evidence Act presumption; failed to explain s.80 IPC not applicable or burden on accused.",
      "addresses_issue": "i3",
      "key_observation": "Mixed ingredients of offence and exception; abdicated function to jury."
    },
    {
      "id": "cr4",
      "text": "Misdirection on grave sudden provocation: Left entirely to jury as fact, though question of law whether wife's confession amounts to provocation by deceased.",
      "addresses_issue": "i3",
      "key_observation": "Error in telling jury entire question one of fact."
    },
    {
      "id": "cr5",
      "text": "Told jury case rests on circumstantial evidence requiring stringent proof, despite direct extra-judicial confession to Puransingh.",
      "addresses_issue": "i3",
      "key_observation": "Confused jury on approach to evidence."
    },
    {
      "id": "cr6",
      "text": "Omission to refer to three letters by Sylvia showing state of mind re marriage with Ahuja.",
      "addresses_issue": "i3",
      "key_observation": "Important for credibility of Sylvia and Nanavati evidence."
    },
    {
      "id": "cr7",
      "text": "s.105 Evidence Act: Burden on accused to rebut presumption of absence of general exceptions like s.80 IPC; prosecution still proves ingredients of offence.",
      "addresses_issue": "i3",
      "key_observation": "No conflict with general burden on prosecution."
    },
    {
      "id": "cr8",
      "text": "No need to decide if provocation question purely fact under Expl.1 Exc.1 s.300 IPC, as AG concedes no misdirection there.",
      "addresses_issue": "i5",
      "key_observation": "Conceded."
    },
    {
      "id": "cr9",
      "text": "Verdict vitiated by misdirections; HC right to review evidence and convict.",
      "addresses_issue": "i4",
      "key_observation": "Perverse and contrary to weight of evidence."
    }
  ],
  "holdings": [
    {
      "id": "h1",
      "text": "Reference under s.307 CrPC competent if two conditions satisfied ex facie; HC then considers entire evidence.",
      "resolves_issue": "i1",
      "in_favor_of": "respondent"
    },
    {
      "id": "h2",
      "text": "HC under s.307(3) CrPC can set aside jury verdict for misdirections or if unreasonable/perverse.",
      "resolves_issue": "i2",
      "in_favor_of": "respondent"
    },
    {
      "id": "h3",
      "text": "Multiple grave misdirections/omissions in charge vitiated verdict.",
      "resolves_issue": "i3",
      "in_favor_of": "respondent"
    },
    {
      "id": "h4",
      "text": "Jury verdict perverse; no reduction to culpable homicide on provocation.",
      "resolves_issue": "i4",
      "in_favor_of": "respondent"
    }
  ],
  "precedents_cited": [
    {
      "case_name": "Ramanugrah Singh v. King Emperor",
      "citation": null,
      "treatment": "followed",
      "relevance": "Construction of s.307 CrPC; ends of justice mean verdict no reasonable body could reach."
    },
    {
      "case_name": "Akhlakali Hayatalli v. The State of Bombay",
      "citation": null,
      "treatment": "followed",
      "relevance": "Wide power under s.307 CrPC; misdirections can vitiate."
    },
    {
      "case_name": "Ratan Rai v. State of Bihar",
      "citation": null,
      "treatment": "followed",
      "relevance": "HC must consider entire evidence and charge under s.307."
    },
    {
      "case_name": "Sashi Mohan Debnath v. The State of West Bengal",
      "citation": null,
      "treatment": "followed",
      "relevance": "Sessions Judge must submit whole case under s.307(2)."
    },
    {
      "case_name": "Emperor v. Ramadhar Kurmi",
      "citation": null,
      "treatment": "referred",
      "relevance": "Misdirection under s.537 CrPC; no weight to erroneous verdict."
    },
    {
      "case_name": "Mushtak Hussein v. The State of Bombay",
      "citation": null,
      "treatment": "followed",
      "relevance": "Misdirection must occasion failure of justice."
    },
    {
      "case_name": "Smt. Nagindra Bala Mitra v. Sunil Chandra Roy",
      "citation": null,
      "treatment": "followed",
      "relevance": "Restates test for misdirection vitiating verdict."
    },
    {
      "case_name": "Holmes v. Director of Public Prosecutions",
      "citation": null,
      "treatment": "distinguished",
      "relevance": "English law on provocation; judge rules if evidence supports."
    },
    {
      "case_name": "Woolmington v. Director of Public Prosecutions",
      "citation": null,
      "treatment": "referred",
      "relevance": "Prosecution proves guilt; accused raises doubt."
    },
    {
      "case_name": "Attygalle v. Emperor",
      "citation": null,
      "treatment": "distinguished",
      "relevance": "s.106 Evidence not casting burden to disprove crime."
    }
  ],
  "statutes_cited": [
    {
      "name": "Indian Penal Code, 1860",
      "sections": [
        "302",
        "304 Part I",
        "80",
        "300 Exception 1"
      ],
      "relevance": "Murder charge; accident exception; provocation reducing to culpable homicide."
    },
    {
      "name": "Code of Criminal Procedure, 1898",
      "sections": [
        "307",
        "297",
        "298",
        "268",
        "410",
        "417",
        "418",
        "423"
      ],
      "relevance": "Reference on jury disagreement; jury trial procedure; appeals limited to law in jury cases."
    },
    {
      "name": "Indian Evidence Act, 1872",
      "sections": [
        "105",
        "103",
        "3",
        "4"
      ],
      "relevance": "Burden on accused for general exceptions; presumption of absence."
    }
  ],
  "outcome": {
    "disposition": "dismissed",
    "summary": "Supreme Court rejected appellant's contentions on procedural points under s.307 CrPC, upheld finding of grave misdirections vitiating jury verdict, confirmed conviction under s.302 IPC and life imprisonment by Bombay High Court.",
    "relief_granted": null,
    "costs": null
  },
  "key_quotes": [
    {
      "text": "The High Court shall give weight to the verdict of the jury but the weight to be given to a verdict depends upon many circumstances-it may be one that no reasonable body of persons could come to it may be a perverse verdict it may be a divided verdict",
      "speaker": "court",
      "significance": "Explains due weight under s.307(3) CrPC."
    },
    {
      "text": "In India, as it is in England, there is a presumption of innocence in favour of the accused as a general rule, and it is the duty of the prosecution to prove the guilt of the accused",
      "speaker": "court",
      "significance": "Clarifies burden of proof alongside s.105 Evidence Act."
    },
    {
      "text": "Unless therefore it is established in a case that there has been a serious misdirection by the judge in charging the jury which has occasioned a failure of justice and has misled the jury in giving its verdict, the verdict of the jury cannot be set aside.",
      "speaker": "court",
      "significance": "Test for vitiation by misdirection."
    }
  ],
  "_case_id": "1961_270",
  "_label": 0,
  "_text_length": 204453,
  "_extracted_at": "2026-02-10T19:33:33.738645"
}