{
  "metadata": {
    "case_name": "Appellant v. Respondent No. 1",
    "case_year": 1968,
    "court": "Supreme Court of India",
    "judges": [
      "Shelat, J."
    ],
    "case_number": "Civil Appeal No. 2331 of 1968",
    "date_of_judgment": null
  },
  "facts": [
    {
      "id": "f1",
      "text": "The appellant filed a writ petition in the High Court at Allahabad for a quo warranto against respondent 1, challenging his appointment as a Judge of that High Court.",
      "type": "procedural",
      "date": null,
      "source": "court"
    },
    {
      "id": "f2",
      "text": "Respondent 1 was enrolled as an advocate more than 20 years ago but was all along practising at Benaras and not in the High Court.",
      "type": "material",
      "date": null,
      "source": "petitioner"
    },
    {
      "id": "f3",
      "text": "The writ petition came up for preliminary hearing before Broome and G. Kumar, JJ.",
      "type": "procedural",
      "date": null,
      "source": "court"
    },
    {
      "id": "f4",
      "text": "Broome, J. held that 'an advocate of a High Court' in Art. 217(2)(b) meant an advocate enrolled as such, irrespective of practice location.",
      "type": "procedural",
      "date": null,
      "source": "lower_court"
    },
    {
      "id": "f5",
      "text": "G. Kumar, J. held that 'an advocate of a High Court' meant one who has practised for the required period in a High Court.",
      "type": "procedural",
      "date": null,
      "source": "lower_court"
    },
    {
      "id": "f6",
      "text": "Matter referred to Mathur, J., who agreed with Broome, J., and the writ petition was dismissed on July 24, 1968.",
      "type": "procedural",
      "date": "1968-07-24",
      "source": "lower_court"
    },
    {
      "id": "f7",
      "text": "High Court granted certificate for appeal to Supreme Court.",
      "type": "procedural",
      "date": null,
      "source": "lower_court"
    }
  ],
  "legal_issues": [
    {
      "id": "i1",
      "text": "Whether 'an advocate of a High Court' in Art. 217(2)(b) means an advocate enrolled as such irrespective of practice location, or one who has practised for at least ten years in a High Court.",
      "framed_by": "petitioner"
    },
    {
      "id": "i2",
      "text": "Whether distinction in language between Art. 217(2)(b), Art. 124(3), and Art. 233(2) requires practice in High Court for judgeship qualification.",
      "framed_by": "petitioner"
    }
  ],
  "petitioner_arguments": [
    {
      "id": "pa1",
      "text": "Expression 'an advocate of a High Court' in Art. 217(2)(b) meant an advocate practising in the High Court and not one practising in courts subordinate to the High Court.",
      "supporting_facts": [
        "f2"
      ],
      "legal_basis": "Art. 217(2)(b); comparison with Art. 124(3) and Art. 233(2)"
    },
    {
      "id": "pa2",
      "text": "Language in Art. 124(3)(a) and (b) distinguishes: 'a judge of a High Court' means one who worked in High Court, similarly 'an advocate of a High Court' means one who practised in High Court.",
      "supporting_facts": [],
      "legal_basis": "Art. 124(3)"
    },
    {
      "id": "pa3",
      "text": "Art. 233(2) uses 'an advocate' simpliciter for district judge, distinguishing from 'advocate of a High Court' for High Court/Supreme Court judges requiring High Court practice.",
      "supporting_facts": [],
      "legal_basis": "Art. 233(2)"
    }
  ],
  "respondent_arguments": [
    {
      "id": "ra1",
      "text": "On a plain reading, 'an advocate of a High Court' means an advocate enrolled as such, irrespective of whether he practised in the High Court or subordinate courts.",
      "supporting_facts": [
        "f2",
        "f4"
      ],
      "legal_basis": "Art. 217(2)(b)"
    }
  ],
  "court_reasoning": [
    {
      "id": "cr1",
      "text": "Language of Art. 217(2)(b) is plain and means a person enrolled as an advocate of a High Court; if practice in High Court required, clause would explicitly say so.",
      "addresses_issue": "i1",
      "key_observation": "Ordinary plain meaning: enrolled advocate."
    },
    {
      "id": "cr2",
      "text": "Historical statutes like Legal Practitioners Act, 1879 (Ss. 3,4,41), Indian Bar Councils Act, 1926 (Ss. 8,9,10,14), Govt. of India Acts 1915 (S.101(3)(d)) and 1935 (S.220(3)(d)) use similar expressions meaning enrolled advocates entitled to practise in High Court or subordinates.",
      "addresses_issue": "i1",
      "key_observation": "Enrolment entitles practice anywhere subordinate or High Court."
    },
    {
      "id": "cr3",
      "text": "Accepting petitioner's view creates anomaly in Art. 124(3): Supreme Court advocate without High Court practice ineligible.",
      "addresses_issue": "i1",
      "key_observation": "Strange anomaly pointed out by Broome, J."
    },
    {
      "id": "cr4",
      "text": "Distinction with Art. 233(2) has no significance post Advocates Act, 1961 (S.16): only senior advocates and other advocates.",
      "addresses_issue": "i2",
      "key_observation": "Post-1961 Act, no distinction."
    }
  ],
  "holdings": [
    {
      "id": "h1",
      "text": "'An advocate of a High Court' in Art. 217(2)(b) and Art. 124(3) means an advocate enrolled on the roll of a High Court, irrespective of practice location.",
      "resolves_issue": "i1",
      "in_favor_of": "respondent"
    },
    {
      "id": "h2",
      "text": "First contention of appellant fails; agrees with Broome and Mathur, JJ.",
      "resolves_issue": "i2",
      "in_favor_of": "respondent"
    }
  ],
  "precedents_cited": [
    {
      "case_name": "Sengalani Gramani v. Subbayya Nadar Ors.",
      "citation": null,
      "treatment": "referred",
      "relevance": "One of two decisions referred to by the Court"
    }
  ],
  "statutes_cited": [
    {
      "name": "Constitution of India",
      "sections": [
        "Art. 217(2)(b)",
        "Art. 124(3)",
        "Art. 233(2)"
      ],
      "relevance": "Qualifications for appointment as Judge of High Court/Supreme Court/District Judge; interpretation of 'advocate of a High Court'"
    },
    {
      "name": "Legal Practitioners Act, 1879",
      "sections": [
        "S. 3",
        "S. 4",
        "S. 41"
      ],
      "relevance": "Definition and rights of advocates enrolled in High Court to practise in High Court or subordinate courts"
    },
    {
      "name": "Indian Bar Councils Act, 1926",
      "sections": [
        "S. 8",
        "S. 9",
        "S. 10",
        "S. 14(1)"
      ],
      "relevance": "Roll of advocates of High Court; entitlement to practise; disciplinary jurisdiction"
    },
    {
      "name": "Government of India Act, 1915",
      "sections": [
        "S. 101(3)(d)"
      ],
      "relevance": "Qualifications for High Court Judge: pleader of High Court for 10 years"
    },
    {
      "name": "Government of India Act, 1935",
      "sections": [
        "S. 220(3)(d)"
      ],
      "relevance": "Qualifications for High Court Judge: pleader of High Court for 10 years, including succession and judicial office"
    },
    {
      "name": "Advocates Act, 1961",
      "sections": [
        "S. 16"
      ],
      "relevance": "Classes of persons entitled to practise: senior advocates and other advocates; impacts distinction post-1961"
    }
  ],
  "outcome": {
    "disposition": "dismissed",
    "summary": "The Supreme Court agreed with Broome and Mathur, JJ. of the Allahabad High Court, holding that respondent 1 qualified under Art. 217(2)(b) as an enrolled advocate of over 10 years, irrespective of practice location. The appeal challenging the dismissal of the writ petition was dismissed.",
    "relief_granted": null,
    "costs": null
  },
  "key_quotes": [
    {
      "text": "The language used in Art. 217(2)(b) is plain and incapable of bearing an interpretation other than the one given by Broome, J., and agreeing with him by Mathur, J.",
      "speaker": "court",
      "significance": "Core holding on plain meaning of the provision"
    },
    {
      "text": "One broad point against the interpretation sought by counsel for the appellant would be that the expression an advocate of a High Court in its ordinary plain meaning must mean a person who has by enrolling himself under the relevant provisions of law become an advocate of a High Court.",
      "speaker": "court",
      "significance": "Rejects requirement of High Court practice"
    },
    {
      "text": "If the meaning of the expression an advocate of a High Court as suggested on behalf of the appellant were to be accepted a very strange anomaly... would result while construing Art. 124(3).",
      "speaker": "court",
      "significance": "Highlights anomaly in petitioner's interpretation"
    }
  ],
  "_case_id": "1969_151",
  "_label": 0,
  "_text_length": 14419,
  "_extracted_at": "2026-02-10T20:26:05.191691"
}