{
  "metadata": {
    "case_name": "Writ Petition No. 467 of 1972 (Petitioner v. State of Gujarat)",
    "case_year": 1972,
    "court": "Supreme Court of India",
    "judges": [
      "UNTWALIA, J."
    ],
    "case_number": "Writ Petition No. 467 of 1972",
    "date_of_judgment": null
  },
  "facts": [
    {
      "id": "f1",
      "text": "Petitioner owns 9559 square yards of land situate in District Bulsar, sub-district and Taluka Navsari, village Kohilpore.",
      "type": "background",
      "date": null,
      "source": "petitioner"
    },
    {
      "id": "f2",
      "text": "Petitioner intends to sell the said land but is unable to do so because of the prohibition of alienation imposed under the Gujarat Vacant Lands in Urban Areas Prohibition of Alienation Act, 1972 (Gujarat Act No. 12 of 1972).",
      "type": "material",
      "date": null,
      "source": "petitioner"
    },
    {
      "id": "f3",
      "text": "Proclamation of Emergency is in operation under Article 358 of the Constitution, suspending fundamental rights under Article 19.",
      "type": "procedural",
      "date": null,
      "source": "court"
    },
    {
      "id": "f4",
      "text": "The Act is a temporary measure originally to remain in force for one year, extended from time to time to enable passage of Urban Property Ceilings Act; prohibition of alienation is preparatory for distribution of material resources.",
      "type": "background",
      "date": null,
      "source": "court"
    },
    {
      "id": "f5",
      "text": "Section 2 of the Act embodies declaration for giving effect to policy towards securing principles in clauses (b) and (c) of Article 39.",
      "type": "background",
      "date": null,
      "source": "court"
    },
    {
      "id": "f6",
      "text": "Preamble: Act to prohibit alienation of certain vacant lands in urban areas to prevent concentration of wealth and distribute material resources for common good.",
      "type": "background",
      "date": null,
      "source": "court"
    },
    {
      "id": "f7",
      "text": "Urban area defined in section 3(i): areas in City or municipal borough, vicinity up to 16 km as notified, or other areas declared urban due to projects.",
      "type": "background",
      "date": null,
      "source": "court"
    },
    {
      "id": "f8",
      "text": "Vacant land defined in section 3(j): land in urban area, agricultural or non-agricultural, other than land on which building constructed or being constructed per law, and appurtenant land to minimum extent.",
      "type": "background",
      "date": null,
      "source": "court"
    },
    {
      "id": "f9",
      "text": "Compact block defined in section 3(d): block of vacant land exceeding 1000 sq m, owned by one or more, or contiguous parts by family unit, whether divided by private road etc.",
      "type": "background",
      "date": null,
      "source": "court"
    },
    {
      "id": "f10",
      "text": "Section 4(1): Prohibits alienation of vacant land on/after appointed day by sale, gift etc., partition, trust; null and void if contravened. Proviso: excludes one plot <=1000 sq m not part of compact block.",
      "type": "background",
      "date": null,
      "source": "court"
    },
    {
      "id": "f11",
      "text": "Section 6: Act does not apply to transfers by/to State/Central Govt, local authority, Govt company, Govt corporation, approved cooperative house building societies for weaker sections.",
      "type": "background",
      "date": null,
      "source": "court"
    },
    {
      "id": "f12",
      "text": "Section 7(1): State Govt may exempt area/alienation for reasons recorded.",
      "type": "background",
      "date": null,
      "source": "court"
    },
    {
      "id": "f13",
      "text": "Section 7(2): State Govt may exempt to avoid hardship.",
      "type": "background",
      "date": null,
      "source": "court"
    },
    {
      "id": "f14",
      "text": "Section 7(3): Collector may exempt for educational, scientific, industrial, commercial or prescribed purposes.",
      "type": "background",
      "date": null,
      "source": "court"
    },
    {
      "id": "f15",
      "text": "Notifications issued fixing distances up to 16 km for big cities like Ahmedabad, Baroda, lesser for small boroughs.",
      "type": "background",
      "date": null,
      "source": "respondent"
    }
  ],
  "legal_issues": [
    {
      "id": "i1",
      "text": "Whether the Act violates Article 14 by denying equal protection of law.",
      "framed_by": "petitioner"
    },
    {
      "id": "i2",
      "text": "Whether Article 31C saves the Act as relatable to Article 39(b) and (c).",
      "framed_by": "petitioner"
    }
  ],
  "petitioner_arguments": [
    {
      "id": "pa1",
      "text": "Limit of prohibition same irrespective of situation and value of vacant land, putting unequals as equals.",
      "supporting_facts": [
        "f2"
      ],
      "legal_basis": "Article 14"
    },
    {
      "id": "pa2",
      "text": "Act does not apply to building lands; building areas left out.",
      "supporting_facts": [
        "f2"
      ],
      "legal_basis": "Article 14"
    },
    {
      "id": "pa3",
      "text": "Discrimination between permissible limit of alienation based on irrational consideration of area forming part of compact block or not.",
      "supporting_facts": [
        "f9"
      ],
      "legal_basis": "Article 14"
    },
    {
      "id": "pa4",
      "text": "No rational basis for not applying Act to alienation in favour of State Govt, Central Govt, local authorities, Govt companies, corporations, cooperative house building societies.",
      "supporting_facts": [
        "f11"
      ],
      "legal_basis": "Article 14"
    },
    {
      "id": "pa5",
      "text": "No guideline provided in section 7 for exercise of power of exemption.",
      "supporting_facts": [
        "f12",
        "f13",
        "f14"
      ],
      "legal_basis": "Article 14"
    },
    {
      "id": "pa6",
      "text": "Act not directly relatable to object of Article 39(b) and (c), so Article 31C cannot protect it.",
      "supporting_facts": [
        "f5"
      ],
      "legal_basis": "Article 31C"
    }
  ],
  "respondent_arguments": [
    {
      "id": "ra1",
      "text": "None of the points urged by petitioner has substance; no violation of Article 14.",
      "supporting_facts": [],
      "legal_basis": "Article 14"
    }
  ],
  "court_reasoning": [
    {
      "id": "cr1",
      "text": "No need to take recourse to Article 31C as Act does not infringe Article 14.",
      "addresses_issue": "i2",
      "key_observation": "Act upheld without Article 31C."
    },
    {
      "id": "cr2",
      "text": "When limit of distance outside city/town differs, not feasible to fix permissible area by value; excluding compact block prevents manipulations by family units.",
      "addresses_issue": "i1",
      "key_observation": "Classification reasonable."
    },
    {
      "id": "cr3",
      "text": "Excluding building lands reasonable as object is to prevent alienation of vacant lands.",
      "addresses_issue": "i1",
      "key_observation": "Distinguishes vacant from building land."
    },
    {
      "id": "cr4",
      "text": "Exemptions for transfers to Govt etc. advance object of Act by aiding distribution and preventing concentration of wealth.",
      "addresses_issue": "i1",
      "key_observation": "Nexus with object."
    },
    {
      "id": "cr5",
      "text": "Guidelines for exemptions: reasons recorded for s7(1), hardship for s7(2), specific purposes for s7(3) as prescribed; supervised by legislature and appeal.",
      "addresses_issue": "i1",
      "key_observation": "Sufficient guidelines and checks."
    },
    {
      "id": "cr6",
      "text": "Classifications reasonable with clear nexus to object; neither puts unequals as equals nor discriminates between equals.",
      "addresses_issue": "i1",
      "key_observation": "No violation of Article 14."
    }
  ],
  "holdings": [
    {
      "id": "h1",
      "text": "The Act does not infringe equal protection under Article 14; classifications reasonable and have nexus with object.",
      "resolves_issue": "i1",
      "in_favor_of": "respondent"
    }
  ],
  "precedents_cited": [],
  "statutes_cited": [
    {
      "name": "Constitution of India",
      "sections": [
        "Article 14",
        "Article 19",
        "Article 32",
        "Article 39(b) and (c)",
        "Article 31C",
        "Article 358"
      ],
      "relevance": "Act challenged for violating Arts 14 and 19; Art 19 suspended; Art 31C invoked but not needed."
    },
    {
      "name": "Gujarat Vacant Lands in Urban Areas (Prohibition of Alienation) Act, 1972",
      "sections": [
        "Section 2",
        "Section 3 (clauses b, c, d, dd, e, i, j)",
        "Section 4",
        "Section 5",
        "Section 6",
        "Section 7",
        "Section 8",
        "Section 9",
        "Section 10",
        "Section 11",
        "Section 12",
        "Section 13"
      ],
      "relevance": "Impugned Act; provisions on prohibition, definitions, exemptions analyzed for Art 14 challenge."
    },
    {
      "name": "Companies Act, 1956",
      "sections": [
        "Section 617"
      ],
      "relevance": "Defines Government Company for exemption under s6."
    },
    {
      "name": "Bombay Provincial Municipal Corporations Act, 1949",
      "sections": [],
      "relevance": "Defines City."
    },
    {
      "name": "Gujarat Municipalities Act, 1963",
      "sections": [],
      "relevance": "Defines municipal borough."
    },
    {
      "name": "Bombay Town Planning Act, 1954",
      "sections": [],
      "relevance": "Relevant for appurtenant land to buildings."
    }
  ],
  "outcome": {
    "disposition": "dismissed",
    "summary": "Writ petition challenging constitutional validity of the Gujarat Vacant Lands in Urban Areas (Prohibition of Alienation) Act, 1972 under Articles 14 and 19 dismissed as Act does not violate Article 14 and Article 19 rights suspended.",
    "relief_granted": "None",
    "costs": "Dismissed with costs."
  },
  "key_quotes": [
    {
      "text": "\"In our opinion it is not necessary in this case to take recourse to Article 31C for upholding the constitutional validity of the Act as it does not infringe the equal protection of law guaranteed under Article 14.\"",
      "speaker": "court",
      "significance": "Core holding on Article 14."
    },
    {
      "text": "\"Classifications are all reasonable and there is a clear nexus between the object of the act and the classifications.\"",
      "speaker": "court",
      "significance": "Explains why no Art 14 violation."
    },
    {
      "text": "\"The object of the Act is to prohibit alienation of the vacant lands so that ultimately the ownership and control of the material resources of the Community may be so distributed as best to sub-serve the common good.\"",
      "speaker": "court",
      "significance": "States purpose justifying classifications."
    }
  ],
  "_case_id": "1974_342",
  "_label": 0,
  "_text_length": 15199,
  "_extracted_at": "2026-02-10T20:06:08.134166"
}